recanime/__init__.py
recanime/anime_store/__init__.py
recanime/anime_store/base.py
recanime/anime_store/excel_store.py
recanime/anime_store/store.py
recanime/recommender/__init__.py
recanime/recommender/base.py
recanime/recommender/layer.py
recanime/recommender/ranking_base_filter/__init__.py
recanime/recommender/ranking_base_filter/model.py
recanime/recommender/ranking_base_filter/predict.py
recanime/schema/__init__.py
recanime/schema/predict.py
recanime/schema/training.py
recanime/schema/user.py
recanime/training/__init__.py
recanime/training/dataset.py
recanime/training/functools.py
recanime/training/trainer.py
recanime/utils/__init__.py
recanime/utils/model_utils.py
recanime/utils/rec_utils.py
recanime/version.py
recanime-0.1.4.dist-info/WHEEL
recanime-0.1.4.dist-info/METADATA
recanime-0.1.4.dist-info/RECORD
